shape_eval/__init__.py
shape_eval/__main__.py
shape_eval/service.py
shape_eval/Docs/changelog.txt
shape_eval/testing/__init__.py
shape_eval/testing/base_test.py
shape_eval/testing/civitai_sample.py
shape_eval/testing/test_service.py
shape_eval-1.0.2.dist-info/METADATA
shape_eval-1.0.2.dist-info/WHEEL
shape_eval-1.0.2.dist-info/licenses/LICENSE.txt
shape_eval-1.0.2.dist-info/RECORD
