Metadata-Version: 2.4
Name: shape_eval
Version: 1.0.2
Summary: object schema evaluation
Project-URL: Homepage, https://github.com/Auttcast/shape_eval
Project-URL: Issues, https://github.com/Auttcast/shape_eval/issues
Author-email: Brandon McCartney <auttcast@gmail.com>
License-Expression: AGPL-3.0-or-later
License-File: LICENSE.txt
Classifier: Programming Language :: Python :: 3
Classifier: Topic :: Software Development :: Libraries
Classifier: Topic :: Software Development :: Libraries :: Python Modules
Classifier: Topic :: Utilities
Requires-Python: >=3.8
